neat_ml_schema/__init__.py
neat_ml_schema/datamodel/__init__.py
neat_ml_schema/datamodel/neat_ml_schema.py
neat_ml_schema/schema/neat_ml_schema.yaml
neat_ml_schema-0.1.11.dist-info/LICENSE
neat_ml_schema-0.1.11.dist-info/WHEEL
neat_ml_schema-0.1.11.dist-info/METADATA
neat_ml_schema-0.1.11.dist-info/RECORD
